{"v":"5.5.7","meta":{"g":"LottieFiles AE 0.1.20","a":"Deniz Erce Alagoz","k":"","d":"","tc":""},"fr":60,"ip":0,"op":188,"w":720,"h":720,"nm":"Explore Compass","ddd":0,"assets":[],"layers":[{"ddd":0,"ind":1,"ty":4,"nm":"NavigationExplore Outlines 2","parent":3,"sr":1,"ks":{"o":{"a":0,"k":100,"ix":11},"r":{"a":1,"k":[{"i":{"x":[0.016],"y":[1]},"o":{"x":[0.68],"y":[0]},"t":0,"s":[0]},{"i":{"x":[0.833],"y":[0.833]},"o":{"x":[1],"y":[0]},"t":59,"s":[380]},{"i":{"x":[0.833],"y":[0.833]},"o":{"x":[0.167],"y":[0.167]},"t":120,"s":[-375]},{"i":{"x":[0.833],"y":[0.833]},"o":{"x":[0.167],"y":[0.167]},"t":130,"s":[-380]},{"i":{"x":[0],"y":[1]},"o":{"x":[0.167],"y":[0.167]},"t":140,"s":[-373]},{"t":150,"s":[-360]}],"ix":10},"p":{"a":0,"k":[18.5,6.5,0],"ix":2},"a":{"a":0,"k":[12,12,0],"ix":1},"s":{"a":0,"k":[988.095,988.095,100],"ix":6}},"ao":0,"ef":[{"ty":25,"nm":"Drop Shadow","np":8,"mn":"ADBE Drop Shadow","ix":1,"en":1,"ef":[{"ty":2,"nm":"Shadow Color","mn":"ADBE Drop Shadow-0001","ix":1,"v":{"a":0,"k":[0,0,0,1],"ix":1}},{"ty":0,"nm":"Opacity","mn":"ADBE Drop Shadow-0002","ix":2,"v":{"a":0,"k":82.5,"ix":2}},{"ty":0,"nm":"Direction","mn":"ADBE Drop Shadow-0003","ix":3,"v":{"a":0,"k":135,"ix":3}},{"ty":0,"nm":"Distance","mn":"ADBE Drop Shadow-0004","ix":4,"v":{"a":0,"k":0,"ix":4}},{"ty":0,"nm":"Softness","mn":"ADBE Drop Shadow-0005","ix":5,"v":{"a":0,"k":89,"ix":5}},{"ty":7,"nm":"Shadow Only","mn":"ADBE Drop Shadow-0006","ix":6,"v":{"a":0,"k":0,"ix":6}}]}],"shapes":[{"ty":"gr","it":[{"ind":0,"ty":"sh","ix":1,"ks":{"a":0,"k":{"i":[[0.015,-0.014],[0,0],[0.01,0],[0.009,0.004],[0.026,0.01],[0,0.026],[-0.016,0.019],[0,0],[-0.014,0],[-0.013,-0.005],[0,0],[0,0],[0.009,-0.03]],"o":[[0,0],[-0.009,0.004],[-0.011,0],[-0.026,0.01],[-0.016,-0.02],[0,-0.026],[0,0],[0.013,-0.005],[0.014,0],[0,0],[0,0],[0.009,0.029],[-0.005,0.019]],"v":[[0.8,0.831],[-3.76,3.911],[-3.79,3.917],[-3.82,3.911],[-3.9,3.911],[-3.925,3.841],[-3.9,3.771],[-0.82,-0.789],[-0.78,-0.797],[-0.74,-0.789],[-0.65,-0.789],[0.83,0.691],[0.83,0.781]],"c":true},"ix":2},"nm":"Path 1","mn":"ADBE Vector Shape - Group","hd":false},{"ind":1,"ty":"sh","ix":2,"ks":{"a":0,"k":{"i":[[0.05,0.034],[0.099,-0.004],[0.071,-0.05],[0,0],[0.035,-0.048],[0,0],[0.013,-0.059],[-0.011,-0.059],[-0.033,-0.05],[-0.05,-0.033],[-0.093,0],[-0.076,0.055],[0,0],[0,0],[0,0],[-0.012,0.059],[0.012,0.059],[0.032,0.051]],"o":[[-0.082,-0.057],[-0.086,0.002],[0,0],[-0.051,0.031],[0,0],[-0.034,0.05],[-0.012,0.059],[0.011,0.06],[0.033,0.051],[0.076,0.055],[0.093,0],[0,0],[0,0],[0,0],[0.034,-0.05],[0.013,-0.059],[-0.01,-0.06],[-0.033,-0.05]],"v":[[5.8,-5.919],[5.52,-5.999],[5.279,-5.919],[-1.33,-1.449],[-1.46,-1.329],[-5.92,5.281],[-5.991,5.446],[-5.993,5.625],[-5.926,5.792],[-5.8,5.92],[-5.54,6.003],[-5.28,5.92],[1.33,1.46],[1.46,1.331],[5.92,-5.279],[5.99,-5.444],[5.992,-5.624],[5.926,-5.791]],"c":true},"ix":2},"nm":"Path 2","mn":"ADBE Vector Shape - Group","hd":false},{"ty":"mm","mm":1,"nm":"Merge Paths 1","mn":"ADBE Vector Filter - Merge","hd":false},{"ty":"fl","c":{"a":0,"k":[1,1,1,1],"ix":4},"o":{"a":0,"k":100,"ix":5},"r":1,"bm":0,"nm":"Fill 1","mn":"ADBE Vector Graphic - Fill","hd":false},{"ty":"tr","p":{"a":0,"k":[12.001,12],"ix":2},"a":{"a":0,"k":[0,0],"ix":1},"s":{"a":0,"k":[100,100],"ix":3},"r":{"a":0,"k":0,"ix":6},"o":{"a":0,"k":100,"ix":7},"sk":{"a":0,"k":0,"ix":4},"sa":{"a":0,"k":0,"ix":5},"nm":"Transform"}],"nm":"Group 1","np":4,"cix":2,"bm":0,"ix":1,"mn":"ADBE Vector Group","hd":false}],"ip":0,"op":230,"st":0,"bm":0},{"ddd":0,"ind":2,"ty":4,"nm":"NavigationExplore Outlines","sr":1,"ks":{"o":{"a":0,"k":100,"ix":11},"r":{"a":0,"k":0,"ix":10},"p":{"a":0,"k":[369.9,353.1,0],"ix":2},"a":{"a":0,"k":[12,12,0],"ix":1},"s":{"a":0,"k":[1383.333,1383.333,100],"ix":6}},"ao":0,"shapes":[{"ty":"gr","it":[{"ind":0,"ty":"sh","ix":1,"ks":{"a":0,"k":{"i":[[-6.627,0],[0,-6.627],[6.627,0],[0,6.627]],"o":[[6.627,0],[0,6.627],[-6.627,0],[0,-6.627]],"v":[[0,-12],[12,0],[0,12],[-12,0]],"c":true},"ix":2},"nm":"Path 1","mn":"ADBE Vector Shape - Group","hd":false},{"ty":"fl","c":{"a":0,"k":[1,0.176000004189,0.33300000359,1],"ix":4},"o":{"a":0,"k":100,"ix":5},"r":1,"bm":0,"nm":"Fill 1","mn":"ADBE Vector Graphic - Fill","hd":false},{"ty":"tr","p":{"a":0,"k":[12,12],"ix":2},"a":{"a":0,"k":[0,0],"ix":1},"s":{"a":0,"k":[100,100],"ix":3},"r":{"a":0,"k":0,"ix":6},"o":{"a":0,"k":100,"ix":7},"sk":{"a":0,"k":0,"ix":4},"sa":{"a":0,"k":0,"ix":5},"nm":"Transform"}],"nm":"Group 2","np":2,"cix":2,"bm":0,"ix":1,"mn":"ADBE Vector Group","hd":false}],"ip":0,"op":230,"st":0,"bm":0},{"ddd":0,"ind":3,"ty":3,"nm":"Form","sr":1,"ks":{"o":{"a":0,"k":0,"ix":11},"r":{"a":0,"k":0,"ix":10},"p":{"a":0,"k":[344,344,0],"ix":2},"a":{"a":0,"k":[0,0,0],"ix":1},"s":{"a":1,"k":[{"i":{"x":[0.667,0.667,0.667],"y":[1,1,1]},"o":{"x":[0.653,0.653,0.333],"y":[0,0,0]},"t":90,"s":[140,140,100]},{"i":{"x":[0.667,0.667,0.667],"y":[1,1,1]},"o":{"x":[0.333,0.333,0.333],"y":[0,0,0]},"t":110,"s":[154,154,100]},{"t":120,"s":[140,140,100]}],"ix":6}},"ao":0,"ip":0,"op":230,"st":0,"bm":0},{"ddd":0,"ind":4,"ty":4,"nm":"Compass","parent":3,"sr":1,"ks":{"o":{"a":0,"k":100,"ix":11},"r":{"a":1,"k":[{"i":{"x":[0.016],"y":[1]},"o":{"x":[0.68],"y":[0]},"t":0,"s":[215]},{"i":{"x":[0.833],"y":[0.833]},"o":{"x":[1],"y":[0]},"t":59,"s":[430]},{"i":{"x":[0.833],"y":[0.833]},"o":{"x":[0.167],"y":[0.167]},"t":120,"s":[-325]},{"i":{"x":[0.833],"y":[0.833]},"o":{"x":[0.167],"y":[0.167]},"t":130,"s":[-330]},{"i":{"x":[0],"y":[1]},"o":{"x":[0.167],"y":[0.167]},"t":140,"s":[-323]},{"t":150,"s":[-325]}],"ix":10},"p":{"a":0,"k":[18.46,6.496,0],"ix":2},"a":{"a":0,"k":[18.46,6.496,0],"ix":1},"s":{"a":0,"k":[90,90,100],"ix":6}},"ao":0,"shapes":[{"ty":"gr","it":[{"ind":0,"ty":"sh","ix":1,"ks":{"a":0,"k":{"i":[[6.63,0],[0,6.63],[-6.63,0],[0,-6.63]],"o":[[-6.63,0],[0,-6.63],[6.63,0],[0,6.63]],"v":[[18.5,18.5],[6.5,6.5],[18.5,-5.5],[30.5,6.5]],"c":true},"ix":2},"nm":"Path 1","mn":"ADBE Vector Shape - Group","hd":false},{"ind":1,"ty":"sh","ix":2,"ks":{"a":0,"k":{"i":[[0.32,0.84],[0,0],[1.48,-3.96],[0,0],[-0.32,-0.85],[0,0],[-1.48,3.96],[0,0]],"o":[[0,0],[-1.48,-3.96],[0,0],[-0.32,0.84],[0,0],[1.48,3.96],[0,0],[0.32,-0.85]],"v":[[60.73,5.49],[22.76,-96.03],[13.24,-96.03],[-24.73,5.49],[-24.73,8.09],[13.24,109.6],[22.76,109.6],[60.73,8.09]],"c":true},"ix":2},"nm":"Path 2","mn":"ADBE Vector Shape - Group","hd":false},{"ty":"st","c":{"a":0,"k":[1,1,1,1],"ix":3},"o":{"a":0,"k":100,"ix":4},"w":{"a":0,"k":1.242,"ix":5},"lc":1,"lj":1,"ml":10,"bm":0,"nm":"Contour 1","mn":"ADBE Vector Graphic - Stroke","hd":false},{"ty":"fl","c":{"a":0,"k":[1,1,1,1],"ix":4},"o":{"a":0,"k":100,"ix":5},"r":1,"bm":0,"nm":"Fond 1","mn":"ADBE Vector Graphic - Fill","hd":false},{"ty":"tr","p":{"a":0,"k":[0,0],"ix":2},"a":{"a":0,"k":[0,0],"ix":1},"s":{"a":0,"k":[100,100],"ix":3},"r":{"a":0,"k":0,"ix":6},"o":{"a":0,"k":100,"ix":7},"sk":{"a":0,"k":0,"ix":4},"sa":{"a":0,"k":0,"ix":5},"nm":"Transform"}],"nm":"Compass","np":4,"cix":2,"bm":0,"ix":1,"mn":"ADBE Vector Group","hd":false}],"ip":0,"op":230,"st":0,"bm":0}],"markers":[]}